lgjsfinance/__init__.py
lgjsfinance/main.py
lgjsfinance-0.0.1.dist-info/LICENSE
lgjsfinance-0.0.1.dist-info/METADATA
lgjsfinance-0.0.1.dist-info/WHEEL
lgjsfinance-0.0.1.dist-info/top_level.txt
lgjsfinance-0.0.1.dist-info/RECORD
