Metadata-Version: 2.1
Name: lgjsfinance
Version: 0.0.1
Summary: LGJS Finance
Home-page: https://liamgenjs.vercel.app
Author: liamgen.js
Author-email: liamgen.js@proton.me
License: BSD 2-clause
Classifier: Development Status :: 1 - Planning
Classifier: Intended Audience :: Science/Research
Classifier: License :: OSI Approved :: BSD License
Classifier: Operating System :: POSIX :: Linux
Classifier: Programming Language :: Python :: 2
Classifier: Programming Language :: Python :: 2.7
Classifier: Programming Language :: Python :: 3
Classifier: Programming Language :: Python :: 3.4
Classifier: Programming Language :: Python :: 3.5
License-File: LICENSE
Requires-Dist: yfinance >=0.2.38
Requires-Dist: matplotlib
Requires-Dist: datetime
Requires-Dist: time
